{
  "codigo": "21021",
  "nombre": "Historia",
  "fecha_consulta": "2026-02-02T21:46:02.749Z",
  "materias": {
    "1164": {
      "nombre": "METODS Y TECNICAS DE LA INVEST H",
      "semestre": "01",
      "grupos": [
        {
          "grupo": "Q201",
          "profesor": "MONTOYA RIVERO PATRICIA MARIA",
          "horarios": [
            {
              "dia": "MA",
              "dia_nombre": "Martes",
              "inicio": "12:00",
              "fin": "14:00"
            },
            {
              "dia": "JU",
              "dia_nombre": "Jueves",
              "inicio": "12:00",
              "fin": "14:00"
            }
          ],
          "salon": "A-1002"
        },
        {
          "grupo": "Q202",
          "profesor": "ALBATCH PEREZ CARLOS DANIEL",
          "horarios": [
            {
              "dia": "MA",
              "dia_nombre": "Martes",
              "inicio": "08:00",
              "fin": "10:00"
            },
            {
              "dia": "JU",
              "dia_nombre": "Jueves",
              "inicio": "08:00",
              "fin": "10:00"
            }
          ],
          "salon": "A-8207"
        },
        {
          "grupo": "Q211",
          "profesor": "FELIX MATAMOROS ROSA",
          "horarios": [
            {
              "dia": "MA",
              "dia_nombre": "Martes",
              "inicio": "12:00",
              "fin": "14:00"
            },
            {
              "dia": "JU",
              "dia_nombre": "Jueves",
              "inicio": "12:00",
              "fin": "14:00"
            }
          ],
          "salon": "A-8206"
        },
        {
          "grupo": "Q212",
          "profesor": "LUNA GARCIA SANDRA NANCY",
          "horarios": [
            {
              "dia": "MA",
              "dia_nombre": "Martes",
              "inicio": "08:00",
              "fin": "10:00"
            },
            {
              "dia": "JU",
              "dia_nombre": "Jueves",
              "inicio": "08:00",
              "fin": "10:00"
            }
          ],
          "salon": "A-1129"
        },
        {
          "grupo": "Q251",
          "profesor": "HIDALGO PEGO MONICA",
          "horarios": [
            {
              "dia": "LU",
              "dia_nombre": "Lunes",
              "inicio": "14:00",
              "fin": "16:00"
            },
            {
              "dia": "MI",
              "dia_nombre": "Miércoles",
              "inicio": "14:00",
              "fin": "16:00"
            }
          ],
          "salon": "A-8206"
        },
        {
          "grupo": "Q261",
          "profesor": "GARCIA CAPISTRAN HUGO",
          "horarios": [
            {
              "dia": "LU",
              "dia_nombre": "Lunes",
              "inicio": "14:00",
              "fin": "16:00"
            },
            {
              "dia": "MI",
              "dia_nombre": "Miércoles",
              "inicio": "14:00",
              "fin": "16:00"
            }
          ],
          "salon": "A-1129"
        }
      ]
    },
    "1263": {
      "nombre": "HISTORIOGRAFIA GENERAL I",
      "semestre": "02",
      "grupos": [
        {
          "grupo": "Q201",
          "profesor": "VEGA RODRIGUEZ HECTOR ALONSO",
          "horarios": [
            {
              "dia": "MA",
              "dia_nombre": "Martes",
              "inicio": "10:00",
              "fin": "12:00"
            },
            {
              "dia": "JU",
              "dia_nombre": "Jueves",
              "inicio": "10:00",
              "fin": "12:00"
            }
          ],
          "salon": "A-8206"
        },
        {
          "grupo": "Q202",
          "profesor": "PEREZ MORALES ENRIQUE",
          "horarios": [
            {
              "dia": "MA",
              "dia_nombre": "Martes",
              "inicio": "10:00",
              "fin": "12:00"
            },
            {
              "dia": "JU",
              "dia_nombre": "Jueves",
              "inicio": "10:00",
              "fin": "12:00"
            }
          ],
          "salon": "A-8207"
        },
        {
          "grupo": "Q251",
          "profesor": "VEGA RODRIGUEZ HECTOR ALONSO",
          "horarios": [
            {
              "dia": "MA",
              "dia_nombre": "Martes",
              "inicio": "18:00",
              "fin": "20:00"
            },
            {
              "dia": "JU",
              "dia_nombre": "Jueves",
              "inicio": "18:00",
              "fin": "20:00"
            }
          ],
          "salon": "A-8206"
        }
      ]
    },
    "1264": {
      "nombre": "MESOAMERICA II",
      "semestre": "02",
      "grupos": [
        {
          "grupo": "Q201",
          "profesor": "ALBATCH PEREZ CARLOS DANIEL",
          "horarios": [
            {
              "dia": "LU",
              "dia_nombre": "Lunes",
              "inicio": "08:00",
              "fin": "10:00"
            },
            {
              "dia": "MI",
              "dia_nombre": "Miércoles",
              "inicio": "08:00",
              "fin": "10:00"
            }
          ],
          "salon": "A-8206"
        },
        {
          "grupo": "Q202",
          "profesor": "GARCIA CAPISTRAN HUGO",
          "horarios": [
            {
              "dia": "LU",
              "dia_nombre": "Lunes",
              "inicio": "08:00",
              "fin": "10:00"
            },
            {
              "dia": "MI",
              "dia_nombre": "Miércoles",
              "inicio": "08:00",
              "fin": "10:00"
            }
          ],
          "salon": "A-8207"
        },
        {
          "grupo": "Q251",
          "profesor": "SOTO ABREGO MIGUEL ANGEL",
          "horarios": [
            {
              "dia": "LU",
              "dia_nombre": "Lunes",
              "inicio": "18:00",
              "fin": "20:00"
            },
            {
              "dia": "MI",
              "dia_nombre": "Miércoles",
              "inicio": "18:00",
              "fin": "20:00"
            }
          ],
          "salon": "A-8206"
        }
      ]
    },
    "1362": {
      "nombre": "EUROPA SIGLOS V XV",
      "semestre": "03",
      "grupos": [
        {
          "grupo": "Q401",
          "profesor": "TIRADO DE SALAZAR RODRIGO OCTAVIO",
          "horarios": [
            {
              "dia": "MA",
              "dia_nombre": "Martes",
              "inicio": "08:00",
              "fin": "10:00"
            },
            {
              "dia": "JU",
              "dia_nombre": "Jueves",
              "inicio": "08:00",
              "fin": "10:00"
            }
          ],
          "salon": "INF.EN JEFA"
        },
        {
          "grupo": "Q402",
          "profesor": "PEZZAT SANCHEZ PAULINA",
          "horarios": [
            {
              "dia": "MA",
              "dia_nombre": "Martes",
              "inicio": "08:00",
              "fin": "10:00"
            },
            {
              "dia": "JU",
              "dia_nombre": "Jueves",
              "inicio": "08:00",
              "fin": "10:00"
            }
          ],
          "salon": "A-726"
        },
        {
          "grupo": "Q451",
          "profesor": "VEGA RODRIGUEZ HECTOR ALONSO",
          "horarios": [
            {
              "dia": "MA",
              "dia_nombre": "Martes",
              "inicio": "16:00",
              "fin": "18:00"
            },
            {
              "dia": "JU",
              "dia_nombre": "Jueves",
              "inicio": "16:00",
              "fin": "18:00"
            }
          ],
          "salon": "A-724"
        }
      ]
    },
    "1461": {
      "nombre": "DIDACTICA DE LA HISTORIA",
      "semestre": "04",
      "grupos": [
        {
          "grupo": "2451",
          "profesor": "SOTO ABREGO MIGUEL ANGEL",
          "horarios": [
            {
              "dia": "LU",
              "dia_nombre": "Lunes",
              "inicio": "16:00",
              "fin": "18:00"
            },
            {
              "dia": "MI",
              "dia_nombre": "Miércoles",
              "inicio": "16:00",
              "fin": "18:00"
            }
          ],
          "salon": "A-726"
        }
      ]
    },
    "1462": {
      "nombre": "EUROPA SIGLOS XVI XVIII",
      "semestre": "04",
      "grupos": [
        {
          "grupo": "2451",
          "profesor": "ABASCAL SHERWELL RAULL PABLO",
          "horarios": [
            {
              "dia": "MA",
              "dia_nombre": "Martes",
              "inicio": "14:00",
              "fin": "16:00"
            },
            {
              "dia": "JU",
              "dia_nombre": "Jueves",
              "inicio": "14:00",
              "fin": "16:00"
            }
          ],
          "salon": "A-8207"
        }
      ]
    },
    "1463": {
      "nombre": "HISTORIA DEL ARTE II",
      "semestre": "04",
      "grupos": [
        {
          "grupo": "Q201",
          "profesor": "MUÑOZ TREJO MELISSA",
          "horarios": [
            {
              "dia": "LU",
              "dia_nombre": "Lunes",
              "inicio": "12:00",
              "fin": "14:00"
            },
            {
              "dia": "MI",
              "dia_nombre": "Miércoles",
              "inicio": "12:00",
              "fin": "14:00"
            }
          ],
          "salon": "A-8206"
        },
        {
          "grupo": "Q202",
          "profesor": "CAMPOS MARES ABIGAIL",
          "horarios": [
            {
              "dia": "LU",
              "dia_nombre": "Lunes",
              "inicio": "12:00",
              "fin": "14:00"
            },
            {
              "dia": "MI",
              "dia_nombre": "Miércoles",
              "inicio": "12:00",
              "fin": "14:00"
            }
          ],
          "salon": "A-8207"
        },
        {
          "grupo": "Q251",
          "profesor": "PAULET QUEVEDO ISARY",
          "horarios": [
            {
              "dia": "MA",
              "dia_nombre": "Martes",
              "inicio": "16:00",
              "fin": "18:00"
            },
            {
              "dia": "JU",
              "dia_nombre": "Jueves",
              "inicio": "16:00",
              "fin": "18:00"
            }
          ],
          "salon": "A-8206"
        }
      ]
    },
    "1464": {
      "nombre": "HISTORIOGRAFIA GENERAL III",
      "semestre": "04",
      "grupos": [
        {
          "grupo": "Q401",
          "profesor": "CRESPO REYES SOFIA",
          "horarios": [
            {
              "dia": "LU",
              "dia_nombre": "Lunes",
              "inicio": "12:00",
              "fin": "14:00"
            },
            {
              "dia": "MI",
              "dia_nombre": "Miércoles",
              "inicio": "12:00",
              "fin": "14:00"
            }
          ],
          "salon": "A-726"
        },
        {
          "grupo": "Q402",
          "profesor": "LOPEZ MORA REBECA",
          "horarios": [
            {
              "dia": "LU",
              "dia_nombre": "Lunes",
              "inicio": "10:00",
              "fin": "12:00"
            },
            {
              "dia": "MI",
              "dia_nombre": "Miércoles",
              "inicio": "10:00",
              "fin": "12:00"
            }
          ],
          "salon": "A-724"
        },
        {
          "grupo": "Q451",
          "profesor": "PUGA HERNANDEZ ALICIA",
          "horarios": [
            {
              "dia": "LU",
              "dia_nombre": "Lunes",
              "inicio": "16:00",
              "fin": "18:00"
            },
            {
              "dia": "MI",
              "dia_nombre": "Miércoles",
              "inicio": "16:00",
              "fin": "18:00"
            }
          ],
          "salon": "A-8209"
        }
      ]
    },
    "1465": {
      "nombre": "NUEVA ESPAÑA SIGLO XVIII",
      "semestre": "04",
      "grupos": [
        {
          "grupo": "Q401",
          "profesor": "LUNA GARCIA SANDRA NANCY",
          "horarios": [
            {
              "dia": "MA",
              "dia_nombre": "Martes",
              "inicio": "10:00",
              "fin": "12:00"
            },
            {
              "dia": "JU",
              "dia_nombre": "Jueves",
              "inicio": "10:00",
              "fin": "12:00"
            }
          ],
          "salon": "A-726"
        },
        {
          "grupo": "Q402",
          "profesor": "CERON RUIZ MIGUEL ANGEL",
          "horarios": [
            {
              "dia": "MA",
              "dia_nombre": "Martes",
              "inicio": "10:00",
              "fin": "12:00"
            },
            {
              "dia": "JU",
              "dia_nombre": "Jueves",
              "inicio": "10:00",
              "fin": "12:00"
            }
          ],
          "salon": "A-724"
        },
        {
          "grupo": "Q451",
          "profesor": "SANCHEZ MUÑOZ DAVID ALEJANDRO",
          "horarios": [
            {
              "dia": "MA",
              "dia_nombre": "Martes",
              "inicio": "14:00",
              "fin": "16:00"
            },
            {
              "dia": "JU",
              "dia_nombre": "Jueves",
              "inicio": "14:00",
              "fin": "16:00"
            }
          ],
          "salon": "A-726"
        }
      ]
    },
    "1563": {
      "nombre": "ESTADOS UNIDOS DE NORTEAMERICA",
      "semestre": "05",
      "grupos": [
        {
          "grupo": "Q201",
          "profesor": "CERVANTES LOPEZ JULIO CESAR",
          "horarios": [
            {
              "dia": "LU",
              "dia_nombre": "Lunes",
              "inicio": "10:00",
              "fin": "12:00"
            },
            {
              "dia": "MI",
              "dia_nombre": "Miércoles",
              "inicio": "10:00",
              "fin": "12:00"
            }
          ],
          "salon": "A-8206"
        },
        {
          "grupo": "Q202",
          "profesor": "GOVANTES MORALES RICARDO",
          "horarios": [
            {
              "dia": "LU",
              "dia_nombre": "Lunes",
              "inicio": "10:00",
              "fin": "12:00"
            },
            {
              "dia": "MI",
              "dia_nombre": "Miércoles",
              "inicio": "10:00",
              "fin": "12:00"
            }
          ],
          "salon": "A-8207"
        },
        {
          "grupo": "Q251",
          "profesor": "FELIX MATAMOROS ROSA",
          "horarios": [
            {
              "dia": "MA",
              "dia_nombre": "Martes",
              "inicio": "14:00",
              "fin": "16:00"
            },
            {
              "dia": "JU",
              "dia_nombre": "Jueves",
              "inicio": "14:00",
              "fin": "16:00"
            }
          ],
          "salon": "A-8206"
        }
      ]
    },
    "1661": {
      "nombre": "AMERICA LATINA SIGLO XX",
      "semestre": "06",
      "grupos": [
        {
          "grupo": "2601",
          "profesor": "PEZZAT SANCHEZ PAULINA",
          "horarios": [
            {
              "dia": "LU",
              "dia_nombre": "Lunes",
              "inicio": "08:00",
              "fin": "10:00"
            },
            {
              "dia": "MI",
              "dia_nombre": "Miércoles",
              "inicio": "08:00",
              "fin": "10:00"
            }
          ],
          "salon": "A-726"
        },
        {
          "grupo": "2602",
          "profesor": "CERVANTES LOPEZ JULIO CESAR",
          "horarios": [
            {
              "dia": "LU",
              "dia_nombre": "Lunes",
              "inicio": "08:00",
              "fin": "10:00"
            },
            {
              "dia": "MI",
              "dia_nombre": "Miércoles",
              "inicio": "08:00",
              "fin": "10:00"
            }
          ],
          "salon": "A-1002"
        },
        {
          "grupo": "2651",
          "profesor": "URBINA MARTINEZ GILBERTO",
          "horarios": [
            {
              "dia": "MA",
              "dia_nombre": "Martes",
              "inicio": "16:00",
              "fin": "18:00"
            },
            {
              "dia": "JU",
              "dia_nombre": "Jueves",
              "inicio": "16:00",
              "fin": "18:00"
            }
          ],
          "salon": "A-8207"
        }
      ]
    },
    "1662": {
      "nombre": "HISTORIA MUNDIAL SIGLO XX I",
      "semestre": "06",
      "grupos": [
        {
          "grupo": "2601",
          "profesor": "GOVANTES MORALES RICARDO",
          "horarios": [
            {
              "dia": "MA",
              "dia_nombre": "Martes",
              "inicio": "08:00",
              "fin": "10:00"
            },
            {
              "dia": "JU",
              "dia_nombre": "Jueves",
              "inicio": "08:00",
              "fin": "10:00"
            }
          ],
          "salon": "INF.EN JEFA"
        },
        {
          "grupo": "2602",
          "profesor": "TIRADO DE SALAZAR RODRIGO OCTAVIO",
          "horarios": [
            {
              "dia": "LU",
              "dia_nombre": "Lunes",
              "inicio": "10:00",
              "fin": "12:00"
            },
            {
              "dia": "MI",
              "dia_nombre": "Miércoles",
              "inicio": "10:00",
              "fin": "12:00"
            }
          ],
          "salon": "A-8209"
        },
        {
          "grupo": "2651",
          "profesor": "CONTRERAS ROMERO VALENTE ALBERTO",
          "horarios": [
            {
              "dia": "LU",
              "dia_nombre": "Lunes",
              "inicio": "16:00",
              "fin": "18:00"
            },
            {
              "dia": "MI",
              "dia_nombre": "Miércoles",
              "inicio": "16:00",
              "fin": "18:00"
            }
          ],
          "salon": "A-8207"
        }
      ]
    },
    "1663": {
      "nombre": "HISTORIOGRAFIA DE MEXICO II",
      "semestre": "06",
      "grupos": [
        {
          "grupo": "2601",
          "profesor": "MONTOYA RIVERO PATRICIA MARIA",
          "horarios": [
            {
              "dia": "MA",
              "dia_nombre": "Martes",
              "inicio": "10:00",
              "fin": "12:00"
            },
            {
              "dia": "JU",
              "dia_nombre": "Jueves",
              "inicio": "10:00",
              "fin": "12:00"
            }
          ],
          "salon": "A-1002"
        },
        {
          "grupo": "2602",
          "profesor": "CAZAREZ MATA JOSE TRINIDAD",
          "horarios": [
            {
              "dia": "MA",
              "dia_nombre": "Martes",
              "inicio": "10:00",
              "fin": "12:00"
            },
            {
              "dia": "JU",
              "dia_nombre": "Jueves",
              "inicio": "10:00",
              "fin": "12:00"
            }
          ],
          "salon": "INF.EN JEFA"
        },
        {
          "grupo": "2651",
          "profesor": "CAZAREZ MATA JOSE TRINIDAD",
          "horarios": [
            {
              "dia": "MA",
              "dia_nombre": "Martes",
              "inicio": "18:00",
              "fin": "20:00"
            },
            {
              "dia": "JU",
              "dia_nombre": "Jueves",
              "inicio": "18:00",
              "fin": "20:00"
            }
          ],
          "salon": "A-8106"
        }
      ]
    },
    "1664": {
      "nombre": "MEXICO SIGLO XIX II",
      "semestre": "06",
      "grupos": [
        {
          "grupo": "2601",
          "profesor": "UGALDE ANDRADE IMELDA PAOLA",
          "horarios": [
            {
              "dia": "LU",
              "dia_nombre": "Lunes",
              "inicio": "10:00",
              "fin": "12:00"
            },
            {
              "dia": "MI",
              "dia_nombre": "Miércoles",
              "inicio": "10:00",
              "fin": "12:00"
            }
          ],
          "salon": "A-8106"
        },
        {
          "grupo": "2602",
          "profesor": "FELIX MATAMOROS ROSA",
          "horarios": [
            {
              "dia": "MA",
              "dia_nombre": "Martes",
              "inicio": "08:00",
              "fin": "10:00"
            },
            {
              "dia": "JU",
              "dia_nombre": "Jueves",
              "inicio": "08:00",
              "fin": "10:00"
            }
          ],
          "salon": "A-1002"
        },
        {
          "grupo": "2651",
          "profesor": "TORRES MEDINA JAVIER",
          "horarios": [
            {
              "dia": "LU",
              "dia_nombre": "Lunes",
              "inicio": "14:00",
              "fin": "16:00"
            },
            {
              "dia": "MI",
              "dia_nombre": "Miércoles",
              "inicio": "14:00",
              "fin": "16:00"
            }
          ],
          "salon": "A-8106"
        }
      ]
    },
    "1861": {
      "nombre": "MEXICO SIGLO XX II",
      "semestre": "08",
      "grupos": [
        {
          "grupo": "2801",
          "profesor": "BONILLA DE LEON LAURA EDITH",
          "horarios": [
            {
              "dia": "LU",
              "dia_nombre": "Lunes",
              "inicio": "10:00",
              "fin": "12:00"
            },
            {
              "dia": "MI",
              "dia_nombre": "Miércoles",
              "inicio": "10:00",
              "fin": "12:00"
            }
          ],
          "salon": "A-726"
        },
        {
          "grupo": "2802",
          "profesor": "URBINA MARTINEZ GILBERTO",
          "horarios": [
            {
              "dia": "LU",
              "dia_nombre": "Lunes",
              "inicio": "10:00",
              "fin": "12:00"
            },
            {
              "dia": "MI",
              "dia_nombre": "Miércoles",
              "inicio": "10:00",
              "fin": "12:00"
            }
          ],
          "salon": "A-8208"
        },
        {
          "grupo": "2851",
          "profesor": "VARGAS OCAÑA CARLOS DAVID",
          "horarios": [
            {
              "dia": "LU",
              "dia_nombre": "Lunes",
              "inicio": "16:00",
              "fin": "18:00"
            },
            {
              "dia": "MI",
              "dia_nombre": "Miércoles",
              "inicio": "16:00",
              "fin": "18:00"
            }
          ],
          "salon": "A-724"
        }
      ]
    },
    "1862": {
      "nombre": "SEMINARIO DE TITULACION",
      "semestre": "08",
      "grupos": [
        {
          "grupo": "2801",
          "profesor": "ALBATCH PEREZ CARLOS DANIEL",
          "horarios": [
            {
              "dia": "VI",
              "dia_nombre": "Viernes",
              "inicio": "10:00",
              "fin": "14:00"
            }
          ],
          "salon": "A-724"
        },
        {
          "grupo": "2802",
          "profesor": "LOPEZ MORA REBECA",
          "horarios": [
            {
              "dia": "VI",
              "dia_nombre": "Viernes",
              "inicio": "10:00",
              "fin": "14:00"
            }
          ],
          "salon": "A-1002"
        },
        {
          "grupo": "2803",
          "profesor": "GARCIA UGARTE MARTA EUGENIA",
          "horarios": [
            {
              "dia": "VI",
              "dia_nombre": "Viernes",
              "inicio": "10:00",
              "fin": "14:00"
            }
          ],
          "salon": "A-904"
        },
        {
          "grupo": "2804",
          "profesor": "GAYTAN HERRERA GRACIELA",
          "horarios": [
            {
              "dia": "VI",
              "dia_nombre": "Viernes",
              "inicio": "12:00",
              "fin": "16:00"
            }
          ],
          "salon": "A-8208"
        },
        {
          "grupo": "2805",
          "profesor": "HERNANDEZ BOLAÑOS IRMA",
          "horarios": [
            {
              "dia": "VI",
              "dia_nombre": "Viernes",
              "inicio": "10:00",
              "fin": "14:00"
            }
          ],
          "salon": "A-8105"
        },
        {
          "grupo": "2806",
          "profesor": "URBINA MARTINEZ GILBERTO",
          "horarios": [
            {
              "dia": "VI",
              "dia_nombre": "Viernes",
              "inicio": "10:00",
              "fin": "14:00"
            }
          ],
          "salon": "A-8206"
        },
        {
          "grupo": "2807",
          "profesor": "Profesor No Asignado",
          "horarios": [
            {
              "dia": "VI",
              "dia_nombre": "Viernes",
              "inicio": "10:00",
              "fin": "14:00"
            }
          ],
          "salon": "A-8106"
        },
        {
          "grupo": "2809",
          "profesor": "PEZZAT SANCHEZ PAULINA",
          "horarios": [
            {
              "dia": "VI",
              "dia_nombre": "Viernes",
              "inicio": "10:00",
              "fin": "14:00"
            }
          ],
          "salon": "A-8207"
        },
        {
          "grupo": "2819",
          "profesor": "CONTRERAS ROMERO VALENTE ALBERTO",
          "horarios": [
            {
              "dia": "VI",
              "dia_nombre": "Viernes",
              "inicio": "16:00",
              "fin": "20:00"
            }
          ],
          "salon": "A-8208"
        }
      ]
    },
    "2265": {
      "nombre": "ESTADOS UNIDOS DE AMERICA",
      "semestre": "02",
      "grupos": [
        {
          "grupo": "2201",
          "profesor": "CERVANTES LOPEZ JULIO CESAR",
          "horarios": [
            {
              "dia": "LU",
              "dia_nombre": "Lunes",
              "inicio": "10:00",
              "fin": "12:00"
            },
            {
              "dia": "MI",
              "dia_nombre": "Miércoles",
              "inicio": "10:00",
              "fin": "12:00"
            }
          ],
          "salon": "A-8206"
        },
        {
          "grupo": "2202",
          "profesor": "GOVANTES MORALES RICARDO",
          "horarios": [
            {
              "dia": "LU",
              "dia_nombre": "Lunes",
              "inicio": "10:00",
              "fin": "12:00"
            },
            {
              "dia": "MI",
              "dia_nombre": "Miércoles",
              "inicio": "10:00",
              "fin": "12:00"
            }
          ],
          "salon": "A-8207"
        },
        {
          "grupo": "2251",
          "profesor": "FELIX MATAMOROS ROSA",
          "horarios": [
            {
              "dia": "MA",
              "dia_nombre": "Martes",
              "inicio": "14:00",
              "fin": "16:00"
            },
            {
              "dia": "JU",
              "dia_nombre": "Jueves",
              "inicio": "14:00",
              "fin": "16:00"
            }
          ],
          "salon": "A-8206"
        }
      ]
    },
    "2266": {
      "nombre": "HISTORIA Y TEORIA DEL ARTE II",
      "semestre": "02",
      "grupos": [
        {
          "grupo": "2201",
          "profesor": "MUÑOZ TREJO MELISSA",
          "horarios": [
            {
              "dia": "LU",
              "dia_nombre": "Lunes",
              "inicio": "12:00",
              "fin": "14:00"
            },
            {
              "dia": "MI",
              "dia_nombre": "Miércoles",
              "inicio": "12:00",
              "fin": "14:00"
            }
          ],
          "salon": "A-8206"
        },
        {
          "grupo": "2202",
          "profesor": "CAMPOS MARES ABIGAIL",
          "horarios": [
            {
              "dia": "LU",
              "dia_nombre": "Lunes",
              "inicio": "12:00",
              "fin": "14:00"
            },
            {
              "dia": "MI",
              "dia_nombre": "Miércoles",
              "inicio": "12:00",
              "fin": "14:00"
            }
          ],
          "salon": "A-8207"
        },
        {
          "grupo": "2251",
          "profesor": "PAULET QUEVEDO ISARY",
          "horarios": [
            {
              "dia": "MA",
              "dia_nombre": "Martes",
              "inicio": "16:00",
              "fin": "18:00"
            },
            {
              "dia": "JU",
              "dia_nombre": "Jueves",
              "inicio": "16:00",
              "fin": "18:00"
            }
          ],
          "salon": "A-8206"
        }
      ]
    },
    "2267": {
      "nombre": "HISTORIOGRAFIA GENERAL I",
      "semestre": "02",
      "grupos": [
        {
          "grupo": "2201",
          "profesor": "VEGA RODRIGUEZ HECTOR ALONSO",
          "horarios": [
            {
              "dia": "MA",
              "dia_nombre": "Martes",
              "inicio": "10:00",
              "fin": "12:00"
            },
            {
              "dia": "JU",
              "dia_nombre": "Jueves",
              "inicio": "10:00",
              "fin": "12:00"
            }
          ],
          "salon": "A-8206"
        },
        {
          "grupo": "2202",
          "profesor": "PEREZ MORALES ENRIQUE",
          "horarios": [
            {
              "dia": "MA",
              "dia_nombre": "Martes",
              "inicio": "10:00",
              "fin": "12:00"
            },
            {
              "dia": "JU",
              "dia_nombre": "Jueves",
              "inicio": "10:00",
              "fin": "12:00"
            }
          ],
          "salon": "A-8207"
        },
        {
          "grupo": "2251",
          "profesor": "VEGA RODRIGUEZ HECTOR ALONSO",
          "horarios": [
            {
              "dia": "MA",
              "dia_nombre": "Martes",
              "inicio": "18:00",
              "fin": "20:00"
            },
            {
              "dia": "JU",
              "dia_nombre": "Jueves",
              "inicio": "18:00",
              "fin": "20:00"
            }
          ],
          "salon": "A-8206"
        }
      ]
    },
    "2268": {
      "nombre": "MEDITERRANEO ANTIGUO I",
      "semestre": "02",
      "grupos": [
        {
          "grupo": "2201",
          "profesor": "PEREZ MORALES ENRIQUE",
          "horarios": [
            {
              "dia": "MA",
              "dia_nombre": "Martes",
              "inicio": "08:00",
              "fin": "10:00"
            },
            {
              "dia": "JU",
              "dia_nombre": "Jueves",
              "inicio": "08:00",
              "fin": "10:00"
            }
          ],
          "salon": "A-8206"
        },
        {
          "grupo": "2202",
          "profesor": "VEGA RODRIGUEZ HECTOR ALONSO",
          "horarios": [
            {
              "dia": "MA",
              "dia_nombre": "Martes",
              "inicio": "12:00",
              "fin": "14:00"
            },
            {
              "dia": "JU",
              "dia_nombre": "Jueves",
              "inicio": "12:00",
              "fin": "14:00"
            }
          ],
          "salon": "A-8207"
        },
        {
          "grupo": "2251",
          "profesor": "SOSA HERNANDEZ GUILLERMO ALFONSO",
          "horarios": [
            {
              "dia": "LU",
              "dia_nombre": "Lunes",
              "inicio": "16:00",
              "fin": "18:00"
            },
            {
              "dia": "MI",
              "dia_nombre": "Miércoles",
              "inicio": "16:00",
              "fin": "18:00"
            }
          ],
          "salon": "A-8206"
        }
      ]
    },
    "2269": {
      "nombre": "METODOS-TECNS.INVESTIG.HISTORICA",
      "semestre": "02",
      "grupos": [
        {
          "grupo": "2201",
          "profesor": "MONTOYA RIVERO PATRICIA MARIA",
          "horarios": [
            {
              "dia": "MA",
              "dia_nombre": "Martes",
              "inicio": "12:00",
              "fin": "14:00"
            },
            {
              "dia": "JU",
              "dia_nombre": "Jueves",
              "inicio": "12:00",
              "fin": "14:00"
            }
          ],
          "salon": "A-1002"
        },
        {
          "grupo": "2202",
          "profesor": "ALBATCH PEREZ CARLOS DANIEL",
          "horarios": [
            {
              "dia": "MA",
              "dia_nombre": "Martes",
              "inicio": "08:00",
              "fin": "10:00"
            },
            {
              "dia": "JU",
              "dia_nombre": "Jueves",
              "inicio": "08:00",
              "fin": "10:00"
            }
          ],
          "salon": "A-8207"
        },
        {
          "grupo": "2211",
          "profesor": "FELIX MATAMOROS ROSA",
          "horarios": [
            {
              "dia": "MA",
              "dia_nombre": "Martes",
              "inicio": "12:00",
              "fin": "14:00"
            },
            {
              "dia": "JU",
              "dia_nombre": "Jueves",
              "inicio": "12:00",
              "fin": "14:00"
            }
          ],
          "salon": "A-8206"
        },
        {
          "grupo": "2212",
          "profesor": "LUNA GARCIA SANDRA NANCY",
          "horarios": [
            {
              "dia": "MA",
              "dia_nombre": "Martes",
              "inicio": "08:00",
              "fin": "10:00"
            },
            {
              "dia": "JU",
              "dia_nombre": "Jueves",
              "inicio": "08:00",
              "fin": "10:00"
            }
          ],
          "salon": "A-1129"
        },
        {
          "grupo": "2251",
          "profesor": "HIDALGO PEGO MONICA",
          "horarios": [
            {
              "dia": "LU",
              "dia_nombre": "Lunes",
              "inicio": "14:00",
              "fin": "16:00"
            },
            {
              "dia": "MI",
              "dia_nombre": "Miércoles",
              "inicio": "14:00",
              "fin": "16:00"
            }
          ],
          "salon": "A-8206"
        },
        {
          "grupo": "2261",
          "profesor": "GARCIA CAPISTRAN HUGO",
          "horarios": [
            {
              "dia": "LU",
              "dia_nombre": "Lunes",
              "inicio": "14:00",
              "fin": "16:00"
            },
            {
              "dia": "MI",
              "dia_nombre": "Miércoles",
              "inicio": "14:00",
              "fin": "16:00"
            }
          ],
          "salon": "A-1129"
        }
      ]
    },
    "2270": {
      "nombre": "PASADO INDIGENA II",
      "semestre": "02",
      "grupos": [
        {
          "grupo": "2201",
          "profesor": "ALBATCH PEREZ CARLOS DANIEL",
          "horarios": [
            {
              "dia": "LU",
              "dia_nombre": "Lunes",
              "inicio": "08:00",
              "fin": "10:00"
            },
            {
              "dia": "MI",
              "dia_nombre": "Miércoles",
              "inicio": "08:00",
              "fin": "10:00"
            }
          ],
          "salon": "A-8206"
        },
        {
          "grupo": "2202",
          "profesor": "GARCIA CAPISTRAN HUGO",
          "horarios": [
            {
              "dia": "LU",
              "dia_nombre": "Lunes",
              "inicio": "08:00",
              "fin": "10:00"
            },
            {
              "dia": "MI",
              "dia_nombre": "Miércoles",
              "inicio": "08:00",
              "fin": "10:00"
            }
          ],
          "salon": "A-8207"
        },
        {
          "grupo": "2251",
          "profesor": "SOTO ABREGO MIGUEL ANGEL",
          "horarios": [
            {
              "dia": "LU",
              "dia_nombre": "Lunes",
              "inicio": "18:00",
              "fin": "20:00"
            },
            {
              "dia": "MI",
              "dia_nombre": "Miércoles",
              "inicio": "18:00",
              "fin": "20:00"
            }
          ],
          "salon": "A-8206"
        }
      ]
    },
    "2465": {
      "nombre": "ENSEÑANZA DE LA HISTORIA I",
      "semestre": "04",
      "grupos": [
        {
          "grupo": "2401",
          "profesor": "Profesor No Asignado",
          "horarios": [
            {
              "dia": "LU",
              "dia_nombre": "Lunes",
              "inicio": "08:00",
              "fin": "10:00"
            },
            {
              "dia": "MI",
              "dia_nombre": "Miércoles",
              "inicio": "08:00",
              "fin": "10:00"
            }
          ],
          "salon": "INF.EN JEFA"
        },
        {
          "grupo": "2402",
          "profesor": "MANDUJANO LOPEZ FABIAN",
          "horarios": [
            {
              "dia": "LU",
              "dia_nombre": "Lunes",
              "inicio": "08:00",
              "fin": "10:00"
            },
            {
              "dia": "MI",
              "dia_nombre": "Miércoles",
              "inicio": "08:00",
              "fin": "10:00"
            }
          ],
          "salon": "INF.EN JEFA"
        },
        {
          "grupo": "2451",
          "profesor": "Profesor No Asignado",
          "horarios": [
            {
              "dia": "LU",
              "dia_nombre": "Lunes",
              "inicio": "18:00",
              "fin": "20:00"
            },
            {
              "dia": "MI",
              "dia_nombre": "Miércoles",
              "inicio": "18:00",
              "fin": "20:00"
            }
          ],
          "salon": "INF.EN JEFA"
        },
        {
          "grupo": "2551",
          "profesor": "Profesor No Asignado",
          "horarios": [],
          "salon": "NULL"
        }
      ]
    },
    "2466": {
      "nombre": "EUROPA, BIZANCIO, MDO.ISLAM.S.V-",
      "semestre": "04",
      "grupos": [
        {
          "grupo": "2401",
          "profesor": "TIRADO DE SALAZAR RODRIGO OCTAVIO",
          "horarios": [
            {
              "dia": "MA",
              "dia_nombre": "Martes",
              "inicio": "08:00",
              "fin": "10:00"
            },
            {
              "dia": "JU",
              "dia_nombre": "Jueves",
              "inicio": "08:00",
              "fin": "10:00"
            }
          ],
          "salon": "INF.EN JEFA"
        },
        {
          "grupo": "2402",
          "profesor": "PEZZAT SANCHEZ PAULINA",
          "horarios": [
            {
              "dia": "MA",
              "dia_nombre": "Martes",
              "inicio": "08:00",
              "fin": "10:00"
            },
            {
              "dia": "JU",
              "dia_nombre": "Jueves",
              "inicio": "08:00",
              "fin": "10:00"
            }
          ],
          "salon": "A-726"
        },
        {
          "grupo": "2451",
          "profesor": "VEGA RODRIGUEZ HECTOR ALONSO",
          "horarios": [
            {
              "dia": "MA",
              "dia_nombre": "Martes",
              "inicio": "16:00",
              "fin": "18:00"
            },
            {
              "dia": "JU",
              "dia_nombre": "Jueves",
              "inicio": "16:00",
              "fin": "18:00"
            }
          ],
          "salon": "A-724"
        }
      ]
    },
    "2467": {
      "nombre": "HISTORIOGRAFIA GENERAL III",
      "semestre": "04",
      "grupos": [
        {
          "grupo": "2401",
          "profesor": "CRESPO REYES SOFIA",
          "horarios": [
            {
              "dia": "LU",
              "dia_nombre": "Lunes",
              "inicio": "12:00",
              "fin": "14:00"
            },
            {
              "dia": "MI",
              "dia_nombre": "Miércoles",
              "inicio": "12:00",
              "fin": "14:00"
            }
          ],
          "salon": "A-726"
        },
        {
          "grupo": "2402",
          "profesor": "LOPEZ MORA REBECA",
          "horarios": [
            {
              "dia": "LU",
              "dia_nombre": "Lunes",
              "inicio": "10:00",
              "fin": "12:00"
            },
            {
              "dia": "MI",
              "dia_nombre": "Miércoles",
              "inicio": "10:00",
              "fin": "12:00"
            }
          ],
          "salon": "A-724"
        },
        {
          "grupo": "2451",
          "profesor": "PUGA HERNANDEZ ALICIA",
          "horarios": [
            {
              "dia": "LU",
              "dia_nombre": "Lunes",
              "inicio": "16:00",
              "fin": "18:00"
            },
            {
              "dia": "MI",
              "dia_nombre": "Miércoles",
              "inicio": "16:00",
              "fin": "18:00"
            }
          ],
          "salon": "A-8209"
        }
      ]
    },
    "2468": {
      "nombre": "NUEVA ESPAÑA II",
      "semestre": "04",
      "grupos": [
        {
          "grupo": "2401",
          "profesor": "LUNA GARCIA SANDRA NANCY",
          "horarios": [
            {
              "dia": "MA",
              "dia_nombre": "Martes",
              "inicio": "10:00",
              "fin": "12:00"
            },
            {
              "dia": "JU",
              "dia_nombre": "Jueves",
              "inicio": "10:00",
              "fin": "12:00"
            }
          ],
          "salon": "A-726"
        },
        {
          "grupo": "2402",
          "profesor": "CERON RUIZ MIGUEL ANGEL",
          "horarios": [
            {
              "dia": "MA",
              "dia_nombre": "Martes",
              "inicio": "10:00",
              "fin": "12:00"
            },
            {
              "dia": "JU",
              "dia_nombre": "Jueves",
              "inicio": "10:00",
              "fin": "12:00"
            }
          ],
          "salon": "A-724"
        },
        {
          "grupo": "2451",
          "profesor": "SANCHEZ MUÑOZ DAVID ALEJANDRO",
          "horarios": [
            {
              "dia": "MA",
              "dia_nombre": "Martes",
              "inicio": "14:00",
              "fin": "16:00"
            },
            {
              "dia": "JU",
              "dia_nombre": "Jueves",
              "inicio": "14:00",
              "fin": "16:00"
            }
          ],
          "salon": "A-726"
        }
      ]
    },
    "2469": {
      "nombre": "PROYECTOS DE GESTION PATRIMONIAL",
      "semestre": "04",
      "grupos": [
        {
          "grupo": "2401",
          "profesor": "FLORES MORENO MARCO ANTONIO",
          "horarios": [
            {
              "dia": "LU",
              "dia_nombre": "Lunes",
              "inicio": "12:00",
              "fin": "14:00"
            },
            {
              "dia": "MI",
              "dia_nombre": "Miércoles",
              "inicio": "12:00",
              "fin": "14:00"
            }
          ],
          "salon": "A-8209"
        },
        {
          "grupo": "2402",
          "profesor": "Profesor No Asignado",
          "horarios": [
            {
              "dia": "LU",
              "dia_nombre": "Lunes",
              "inicio": "10:00",
              "fin": "12:00"
            },
            {
              "dia": "MI",
              "dia_nombre": "Miércoles",
              "inicio": "10:00",
              "fin": "12:00"
            }
          ],
          "salon": "INF.EN JEFA"
        },
        {
          "grupo": "2451",
          "profesor": "Profesor No Asignado",
          "horarios": [
            {
              "dia": "LU",
              "dia_nombre": "Lunes",
              "inicio": "14:00",
              "fin": "16:00"
            },
            {
              "dia": "MI",
              "dia_nombre": "Miércoles",
              "inicio": "14:00",
              "fin": "16:00"
            }
          ],
          "salon": "INF.EN JEFA"
        }
      ]
    },
    "2470": {
      "nombre": "TEORIA DE LA HISTORIA II",
      "semestre": "04",
      "grupos": [
        {
          "grupo": "2401",
          "profesor": "PEREZ MORALES ENRIQUE",
          "horarios": [
            {
              "dia": "MA",
              "dia_nombre": "Martes",
              "inicio": "12:00",
              "fin": "14:00"
            },
            {
              "dia": "JU",
              "dia_nombre": "Jueves",
              "inicio": "12:00",
              "fin": "14:00"
            }
          ],
          "salon": "INF.EN JEFA"
        },
        {
          "grupo": "2402",
          "profesor": "CRESPO REYES SOFIA",
          "horarios": [
            {
              "dia": "MA",
              "dia_nombre": "Martes",
              "inicio": "12:00",
              "fin": "14:00"
            },
            {
              "dia": "JU",
              "dia_nombre": "Jueves",
              "inicio": "12:00",
              "fin": "14:00"
            }
          ],
          "salon": "INF.EN JEFA"
        },
        {
          "grupo": "2451",
          "profesor": "ORDOÑEZ AGUILAR MANUEL",
          "horarios": [
            {
              "dia": "MA",
              "dia_nombre": "Martes",
              "inicio": "18:00",
              "fin": "20:00"
            },
            {
              "dia": "JU",
              "dia_nombre": "Jueves",
              "inicio": "18:00",
              "fin": "20:00"
            }
          ],
          "salon": "INF.EN JEFA"
        }
      ]
    },
    "0061": {
      "nombre": "TEM.SEL.ICONOGRAF.Y EPIGRAF.MESO",
      "semestre": "40",
      "grupos": [
        {
          "grupo": "2601",
          "profesor": "GARCIA CAPISTRAN HUGO",
          "horarios": [
            {
              "dia": "LU",
              "dia_nombre": "Lunes",
              "inicio": "12:00",
              "fin": "14:00"
            },
            {
              "dia": "MI",
              "dia_nombre": "Miércoles",
              "inicio": "12:00",
              "fin": "14:00"
            }
          ],
          "salon": "A-8106"
        }
      ]
    },
    "0079": {
      "nombre": "TEM. SEL. RELIGIONES MESOAMERICA",
      "semestre": "40",
      "grupos": [
        {
          "grupo": "2601",
          "profesor": "SANCHEZ MUÑOZ DAVID ALEJANDRO",
          "horarios": [
            {
              "dia": "MA",
              "dia_nombre": "Martes",
              "inicio": "12:00",
              "fin": "14:00"
            },
            {
              "dia": "JU",
              "dia_nombre": "Jueves",
              "inicio": "12:00",
              "fin": "14:00"
            }
          ],
          "salon": "INF.EN JEFA"
        }
      ]
    },
    "0054": {
      "nombre": "TEM.SEL.HISTOR.SOCIAL DE LA NVA.",
      "semestre": "40",
      "grupos": [
        {
          "grupo": "2602",
          "profesor": "CERON RUIZ MIGUEL ANGEL",
          "horarios": [
            {
              "dia": "MA",
              "dia_nombre": "Martes",
              "inicio": "14:00",
              "fin": "16:00"
            },
            {
              "dia": "JU",
              "dia_nombre": "Jueves",
              "inicio": "14:00",
              "fin": "16:00"
            }
          ],
          "salon": "A-8208"
        }
      ]
    },
    "0066": {
      "nombre": "TEM. SEL. INSTITUCIONES NOVOHISP",
      "semestre": "40",
      "grupos": [
        {
          "grupo": "2602",
          "profesor": "QUIJANO VELASCO FRANCISCO",
          "horarios": [
            {
              "dia": "VI",
              "dia_nombre": "Viernes",
              "inicio": "10:00",
              "fin": "14:00"
            }
          ],
          "salon": "A-8209"
        },
        {
          "grupo": "2802",
          "profesor": "ABADIA QUINTERO CAROLINA",
          "horarios": [
            {
              "dia": "MA",
              "dia_nombre": "Martes",
              "inicio": "12:00",
              "fin": "16:00"
            }
          ],
          "salon": "INF.EN JEFA"
        }
      ]
    },
    "0033": {
      "nombre": "TEM. SEL. CINE RADIO Y TELEVISIO",
      "semestre": "40",
      "grupos": [
        {
          "grupo": "2604",
          "profesor": "BONILLA DE LEON LAURA EDITH",
          "horarios": [
            {
              "dia": "LU",
              "dia_nombre": "Lunes",
              "inicio": "12:00",
              "fin": "14:00"
            },
            {
              "dia": "MI",
              "dia_nombre": "Miércoles",
              "inicio": "12:00",
              "fin": "14:00"
            }
          ],
          "salon": "INF.EN JEFA"
        }
      ]
    },
    "0028": {
      "nombre": "TEM. SEL. CULTURA MEXICANA SIGLO",
      "semestre": "40",
      "grupos": [
        {
          "grupo": "2607",
          "profesor": "URBINA MARTINEZ GILBERTO",
          "horarios": [
            {
              "dia": "MA",
              "dia_nombre": "Martes",
              "inicio": "12:00",
              "fin": "14:00"
            },
            {
              "dia": "JU",
              "dia_nombre": "Jueves",
              "inicio": "12:00",
              "fin": "14:00"
            }
          ],
          "salon": "A-8208"
        }
      ]
    },
    "0041": {
      "nombre": "TEM. SEL. GUERRA FRIA",
      "semestre": "40",
      "grupos": [
        {
          "grupo": "2609",
          "profesor": "URBINA MARTINEZ GILBERTO",
          "horarios": [
            {
              "dia": "MA",
              "dia_nombre": "Martes",
              "inicio": "14:00",
              "fin": "16:00"
            },
            {
              "dia": "JU",
              "dia_nombre": "Jueves",
              "inicio": "14:00",
              "fin": "16:00"
            }
          ],
          "salon": "A-1129"
        }
      ]
    },
    "0067": {
      "nombre": "TEM. SEL. JAPON SIGLO XX",
      "semestre": "40",
      "grupos": [
        {
          "grupo": "2609",
          "profesor": "MANDUJANO LOPEZ FABIAN",
          "horarios": [
            {
              "dia": "VI",
              "dia_nombre": "Viernes",
              "inicio": "10:00",
              "fin": "14:00"
            }
          ],
          "salon": "A-1129"
        }
      ]
    },
    "0048": {
      "nombre": "TEM.SEL.HISTOR.ECONOMICA DE MESO",
      "semestre": "40",
      "grupos": [
        {
          "grupo": "2801",
          "profesor": "SANCHEZ MUÑOZ DAVID ALEJANDRO",
          "horarios": [
            {
              "dia": "MA",
              "dia_nombre": "Martes",
              "inicio": "10:00",
              "fin": "12:00"
            },
            {
              "dia": "JU",
              "dia_nombre": "Jueves",
              "inicio": "10:00",
              "fin": "12:00"
            }
          ],
          "salon": "A-8208"
        }
      ]
    },
    "0058": {
      "nombre": "TEM.SEL.HISTORIOGRAFIA SOBRE MES",
      "semestre": "40",
      "grupos": [
        {
          "grupo": "2801",
          "profesor": "ALBATCH PEREZ CARLOS DANIEL",
          "horarios": [
            {
              "dia": "MA",
              "dia_nombre": "Martes",
              "inicio": "12:00",
              "fin": "14:00"
            },
            {
              "dia": "JU",
              "dia_nombre": "Jueves",
              "inicio": "12:00",
              "fin": "14:00"
            }
          ],
          "salon": "A-8106"
        }
      ]
    },
    "0068": {
      "nombre": "TEM. SEL. LITERATURA MESOAMERICA",
      "semestre": "40",
      "grupos": [
        {
          "grupo": "2801",
          "profesor": "SALDIERNA RANGEL JOSE JULIAN",
          "horarios": [
            {
              "dia": "LU",
              "dia_nombre": "Lunes",
              "inicio": "14:00",
              "fin": "16:00"
            },
            {
              "dia": "MI",
              "dia_nombre": "Miércoles",
              "inicio": "14:00",
              "fin": "16:00"
            }
          ],
          "salon": "A-8107"
        }
      ]
    },
    "0031": {
      "nombre": "TEM. SEL. CULTURA NOVOHISPANA",
      "semestre": "40",
      "grupos": [
        {
          "grupo": "2802",
          "profesor": "DIAZ MIRANDA LORENZA ELENA",
          "horarios": [
            {
              "dia": "MA",
              "dia_nombre": "Martes",
              "inicio": "10:00",
              "fin": "12:00"
            },
            {
              "dia": "JU",
              "dia_nombre": "Jueves",
              "inicio": "10:00",
              "fin": "12:00"
            }
          ],
          "salon": "INF.EN JEFA"
        }
      ]
    },
    "0050": {
      "nombre": "TEM.SEL.HISTOR.ECONOMICA DE NVA.",
      "semestre": "40",
      "grupos": [
        {
          "grupo": "2802",
          "profesor": "CERVANTES LOPEZ JULIO CESAR",
          "horarios": [
            {
              "dia": "LU",
              "dia_nombre": "Lunes",
              "inicio": "12:00",
              "fin": "14:00"
            },
            {
              "dia": "MI",
              "dia_nombre": "Miércoles",
              "inicio": "12:00",
              "fin": "14:00"
            }
          ],
          "salon": "INF.EN JEFA"
        }
      ]
    },
    "0045": {
      "nombre": "TEM.SEL.HISTOR.DE CIENCIA MEXIC.",
      "semestre": "40",
      "grupos": [
        {
          "grupo": "2804",
          "profesor": "GOVANTES MORALES RICARDO",
          "horarios": [
            {
              "dia": "MA",
              "dia_nombre": "Martes",
              "inicio": "12:00",
              "fin": "14:00"
            },
            {
              "dia": "JU",
              "dia_nombre": "Jueves",
              "inicio": "12:00",
              "fin": "14:00"
            }
          ],
          "salon": "A-8105"
        }
      ]
    },
    "0055": {
      "nombre": "TEM. SEL. HISTOR. SOCIAL MEXICO",
      "semestre": "40",
      "grupos": [
        {
          "grupo": "2804",
          "profesor": "CAMPOS MARES ABIGAIL",
          "horarios": [
            {
              "dia": "LU",
              "dia_nombre": "Lunes",
              "inicio": "14:00",
              "fin": "16:00"
            },
            {
              "dia": "MI",
              "dia_nombre": "Miércoles",
              "inicio": "14:00",
              "fin": "16:00"
            }
          ],
          "salon": "A-726"
        }
      ]
    },
    "0080": {
      "nombre": "TEM.SEL.RELS. DIPLOMAT. MEXICO S",
      "semestre": "40",
      "grupos": [
        {
          "grupo": "2804",
          "profesor": "CRUZADO CAMPOS CARLOS GABRIEL",
          "horarios": [
            {
              "dia": "LU",
              "dia_nombre": "Lunes",
              "inicio": "12:00",
              "fin": "14:00"
            },
            {
              "dia": "MI",
              "dia_nombre": "Miércoles",
              "inicio": "12:00",
              "fin": "14:00"
            }
          ],
          "salon": "A-8208"
        }
      ]
    },
    "0022": {
      "nombre": "TEM. SEL. ARTE COLONIAL MEXICANO",
      "semestre": "40",
      "grupos": [
        {
          "grupo": "2807",
          "profesor": "MUÑOZ TREJO MELISSA",
          "horarios": [
            {
              "dia": "LU",
              "dia_nombre": "Lunes",
              "inicio": "14:00",
              "fin": "16:00"
            },
            {
              "dia": "MI",
              "dia_nombre": "Miércoles",
              "inicio": "14:00",
              "fin": "16:00"
            }
          ],
          "salon": "INF.EN JEFA"
        }
      ]
    },
    "0024": {
      "nombre": "TEM. SEL. ARTE MESOAMERICANO",
      "semestre": "40",
      "grupos": [
        {
          "grupo": "2807",
          "profesor": "GARCIA CAPISTRAN HUGO",
          "horarios": [
            {
              "dia": "MA",
              "dia_nombre": "Martes",
              "inicio": "12:00",
              "fin": "14:00"
            },
            {
              "dia": "JU",
              "dia_nombre": "Jueves",
              "inicio": "12:00",
              "fin": "14:00"
            }
          ],
          "salon": "INF.EN JEFA"
        }
      ]
    },
    "0074": {
      "nombre": "TEM. SEL. PERIODISMO EN MEXICO S",
      "semestre": "40",
      "grupos": [
        {
          "grupo": "2807",
          "profesor": "CRUZ GARCIA RICARDO",
          "horarios": [
            {
              "dia": "MA",
              "dia_nombre": "Martes",
              "inicio": "14:00",
              "fin": "16:00"
            },
            {
              "dia": "JU",
              "dia_nombre": "Jueves",
              "inicio": "14:00",
              "fin": "16:00"
            }
          ],
          "salon": "INF.EN JEFA"
        }
      ]
    },
    "0020": {
      "nombre": "TEM. SEL. AFRICA SIGLO XI",
      "semestre": "40",
      "grupos": [
        {
          "grupo": "2809",
          "profesor": "MANDUJANO LOPEZ FABIAN",
          "horarios": [
            {
              "dia": "MA",
              "dia_nombre": "Martes",
              "inicio": "14:00",
              "fin": "16:00"
            },
            {
              "dia": "JU",
              "dia_nombre": "Jueves",
              "inicio": "14:00",
              "fin": "16:00"
            }
          ],
          "salon": "A-724"
        }
      ]
    },
    "0034": {
      "nombre": "TEM. SEL. CHINA SIGLO XX",
      "semestre": "40",
      "grupos": [
        {
          "grupo": "2809",
          "profesor": "MANDUJANO LOPEZ FABIAN",
          "horarios": [
            {
              "dia": "MA",
              "dia_nombre": "Martes",
              "inicio": "10:00",
              "fin": "12:00"
            },
            {
              "dia": "JU",
              "dia_nombre": "Jueves",
              "inicio": "10:00",
              "fin": "12:00"
            }
          ],
          "salon": "A-1129"
        }
      ]
    },
    "0070": {
      "nombre": "TEM. SEL. MEDIO ORIENTE SIGLO XX",
      "semestre": "40",
      "grupos": [
        {
          "grupo": "2809",
          "profesor": "TIRADO DE SALAZAR RODRIGO OCTAVIO",
          "horarios": [
            {
              "dia": "LU",
              "dia_nombre": "Lunes",
              "inicio": "14:00",
              "fin": "16:00"
            },
            {
              "dia": "MI",
              "dia_nombre": "Miércoles",
              "inicio": "14:00",
              "fin": "16:00"
            }
          ],
          "salon": "A-724"
        }
      ]
    }
  }
}