{
  "fecha_actualizacion": "2026-01-23T09:32:04.976Z",
  "total_carreras": 17,
  "carreras": {
    "20121": {
      "codigo": "20121",
      "nombre": "Arquitectura",
      "hash": "b37af9f1a401405d0296eaff4c89c8e264d44820fbe7549360d9c977c22b55c8",
      "last_changed": "2026-01-23T09:32:04.976Z"
    },
    "20226": {
      "codigo": "20226",
      "nombre": "Diseño Gráfico",
      "hash": "21375cf5c82112ae05f6d8e6f1a80634d8b4f060cc1a5639604b06d59056c0e3",
      "last_changed": "2026-01-23T09:32:04.976Z"
    },
    "20321": {
      "codigo": "20321",
      "nombre": "Actuaría",
      "hash": "00e509075a378e5c48ada0dfb66243bea313f192dd54e2c438901931fabafe4e",
      "last_changed": "2026-01-23T09:32:04.976Z"
    },
    "20421": {
      "codigo": "20421",
      "nombre": "Relaciones Internacionales",
      "hash": "a1bca69c5f1fe78e194fa27ba4794da129cc8e773592059cd24e6350239152ec",
      "last_changed": "2026-01-23T09:32:04.976Z"
    },
    "20422": {
      "codigo": "20422",
      "nombre": "Ciencias Políticas y Admon. Pública",
      "hash": "c1107415a14ec329a75b31a183b5a9b1e346f2e0e0e36de927bf74df352182dd",
      "last_changed": "2026-01-23T09:32:04.976Z"
    },
    "20423": {
      "codigo": "20423",
      "nombre": "Sociología",
      "hash": "e89e08a5a15f6e698983d12b752ec807822c94c2b2b2717cabe91cd27d3b9467",
      "last_changed": "2026-01-23T09:32:04.976Z"
    },
    "20424": {
      "codigo": "20424",
      "nombre": "Periodismo y Comunicación Colectiva",
      "hash": "9d59bab832f3ffa31b36c6e54e2c311a2a759d1028862157ee467f95ef53b41f",
      "last_changed": "2026-01-23T09:32:04.976Z"
    },
    "20425": {
      "codigo": "20425",
      "nombre": "Comunicación",
      "hash": "f21a49c89e4057bdc1f0f8f29a6711cfbe148f4d7ae651d8a9a75f7f2f18a7a4",
      "last_changed": "2026-01-23T09:32:04.976Z"
    },
    "20721": {
      "codigo": "20721",
      "nombre": "Derecho",
      "hash": "60b22cf7821cd7c356bbb0408a0bed8b6a7b0e84d9d51c269fef265b25f7d899",
      "last_changed": "2026-01-23T09:32:04.976Z"
    },
    "20821": {
      "codigo": "20821",
      "nombre": "Economía",
      "hash": "e7f92dd20f7b07d7fb76afae28eeeddbd9608d031b6ffa272cf19e4b31d2aa8e",
      "last_changed": "2026-01-23T09:32:04.976Z"
    },
    "21011": {
      "codigo": "21011",
      "nombre": "Filosofía",
      "hash": "a29fa7587784055e79b5a0ecda47004da1f0697fb0f951368a889fa32c901f8e",
      "last_changed": "2026-01-23T09:32:04.976Z"
    },
    "21013": {
      "codigo": "21013",
      "nombre": "Lengua y Literatura Hispánicas",
      "hash": "c3361e5bbdbc6c209725b862d23a383aa6ab0192ee146f1310e32c9b7b235b36",
      "last_changed": "2026-01-23T09:32:04.976Z"
    },
    "21021": {
      "codigo": "21021",
      "nombre": "Historia",
      "hash": "3ff82dde0642c6c2c31147ab63d98d9acf4601bf55bcfa127dc2ca1901b35911",
      "last_changed": "2026-01-23T09:32:04.976Z"
    },
    "21025": {
      "codigo": "21025",
      "nombre": "Pedagogía",
      "hash": "e5edecce70b1d3ad87f74781829115114f9ccb70b21a7e6bfd61a7b2f0a96d7c",
      "last_changed": "2026-01-23T09:32:04.976Z"
    },
    "21121": {
      "codigo": "21121",
      "nombre": "Ingeniería Civil",
      "hash": "20d3f297aa6d03c1c80ed20a54369436c2053bbc96325ff95c71b643e493243e",
      "last_changed": "2026-01-23T09:32:04.976Z"
    },
    "24022": {
      "codigo": "24022",
      "nombre": "Matemáticas. Apl. y Comp.",
      "hash": "7f1f60a0fc23c92e02f68df1f883d2f0d33b2db9068cfadf938667e419c84b6d",
      "last_changed": "2026-01-23T09:32:04.976Z"
    },
    "24121": {
      "codigo": "24121",
      "nombre": "Enseñanza de Inglés",
      "hash": "19d113c2ff0e408798ab6751bb2a16c6702e2c3f1f43fd28bd0ae8bb631bf32a",
      "last_changed": "2026-01-23T09:32:04.976Z"
    }
  },
  "carreras_faltantes": []
}